setup.py
hw_bonus_point_api/TZ1.py
hw_bonus_point_api/TZ2.py
hw_bonus_point_api/TZ3.py
hw_bonus_point_api/TZ4.py
hw_bonus_point_api/TZ5.py
hw_bonus_point_api/TZ6.py
hw_bonus_point_api/TZ7.py
hw_bonus_point_api/TZ8.py
hw_bonus_point_api/__init__.py
hw_bonus_point_api.egg-info/PKG-INFO
hw_bonus_point_api.egg-info/SOURCES.txt
hw_bonus_point_api.egg-info/dependency_links.txt
hw_bonus_point_api.egg-info/requires.txt
hw_bonus_point_api.egg-info/top_level.txt